odoo/addons/energy_communities_mass_mailing/__init__.py
odoo/addons/energy_communities_mass_mailing/__manifest__.py
odoo/addons/energy_communities_mass_mailing/i18n/ca_ES.po
odoo/addons/energy_communities_mass_mailing/i18n/es.po
odoo/addons/energy_communities_mass_mailing/i18n/eu_ES.po
odoo/addons/energy_communities_mass_mailing/models/__init__.py
odoo/addons/energy_communities_mass_mailing/models/mailing.py
odoo/addons/energy_communities_mass_mailing/models/mailing_contact.py
odoo/addons/energy_communities_mass_mailing/models/mailing_list.py
odoo/addons/energy_communities_mass_mailing/models/utm.py
odoo/addons/energy_communities_mass_mailing/report/__init__.py
odoo/addons/energy_communities_mass_mailing/report/mailing_trace_report.py
odoo/addons/energy_communities_mass_mailing/security/ir.model.access.csv
odoo/addons/energy_communities_mass_mailing/security/ir_rule_data.xml
odoo/addons/energy_communities_mass_mailing/security/res_users_role_data.xml
odoo/addons/energy_communities_mass_mailing/views/mailing_contact_views.xml
odoo/addons/energy_communities_mass_mailing/views/mailing_list_views.xml
odoo/addons/energy_communities_mass_mailing/views/mailing_mailing_views.xml
odoo/addons/energy_communities_mass_mailing/views/mailing_mailing_views_menus.xml
odoo/addons/energy_communities_mass_mailing/views/utm_views.xml
odoo/addons/energy_communities_mass_mailing/wizards/__init__.py
odoo/addons/energy_communities_mass_mailing/wizards/mail_compose_message.py
odoo/addons/energy_communities_mass_mailing/wizards/mail_compose_message_views.xml
odoo/addons/energy_communities_mass_mailing/wizards/multicompany_easy_creation.py
odoo/addons/energy_communities_mass_mailing/wizards/partner_mail_list_wizard.py
odoo/addons/energy_communities_mass_mailing/wizards/partner_mail_list_wizard.xml
odoo14_addon_energy_communities_mass_mailing-14.0.0.1.7.dist-info/METADATA
odoo14_addon_energy_communities_mass_mailing-14.0.0.1.7.dist-info/WHEEL
odoo14_addon_energy_communities_mass_mailing-14.0.0.1.7.dist-info/top_level.txt
odoo14_addon_energy_communities_mass_mailing-14.0.0.1.7.dist-info/RECORD
